Prateek_STT/init.py
Prateek_STT-0.1.dist-info/METADATA
Prateek_STT-0.1.dist-info/WHEEL
Prateek_STT-0.1.dist-info/top_level.txt
Prateek_STT-0.1.dist-info/RECORD
