Metadata-Version: 2.1
Name: Prateek-STT
Version: 0.1
Summary: This is Speech To Text created by Mr.PRATEEK
Author: Prateek Shakya
Author-email: prateekshakya251@gmail.com
